Metadata-Version: 1.0
Name: paiostest
Version: 0.1.1
Summary: UNKNOWN
Home-page: https://github.com/snowroll/python-sdk.git
Author: yanganbao
Author-email: 1399337915@qq.com
License: MIT License
Platform: UNKNOWN
